README.md
bd_to_avp/__init__.py
bd_to_avp/__main__.py
bd_to_avp/app.py
bd_to_avp/bin/FRIM_x64_version_1.31/x64/15dd936825ad475ea34e35f3f54217a6/mfxplugin64_hevcd_sw.dll
bd_to_avp/bin/FRIM_x64_version_1.31/x64/15dd936825ad475ea34e35f3f54217a6/plugin.cfg
bd_to_avp/bin/FRIM_x64_version_1.31/x64/2fca99749fdb49aeb121a5b63ef568f7/mfxplugin64_hevce_sw.dll
bd_to_avp/bin/FRIM_x64_version_1.31/x64/2fca99749fdb49aeb121a5b63ef568f7/plugin.cfg
bd_to_avp/bin/FRIM_x64_version_1.31/x64/588f1185d47b42968dea377bb5d0dcb4/mfxplugin32_h264la_hw.dll
bd_to_avp/bin/FRIM_x64_version_1.31/x64/588f1185d47b42968dea377bb5d0dcb4/mfxplugin64_h264la_hw.dll
bd_to_avp/bin/FRIM_x64_version_1.31/x64/588f1185d47b42968dea377bb5d0dcb4/plugin.cfg
bd_to_avp/bin/FRIM_x64_version_1.31/x64/FRIMDecode64.exe
bd_to_avp/bin/FRIM_x64_version_1.31/x64/FRIMEncode64.exe
bd_to_avp/bin/FRIM_x64_version_1.31/x64/FRIMExport.prm
bd_to_avp/bin/FRIM_x64_version_1.31/x64/FRIMImport.prm
bd_to_avp/bin/FRIM_x64_version_1.31/x64/FRIMSource64.dll
bd_to_avp/bin/FRIM_x64_version_1.31/x64/FRIMTranscode64.exe
bd_to_avp/bin/FRIM_x64_version_1.31/x64/Pattern_3D-TAB.prproj
bd_to_avp/bin/FRIM_x64_version_1.31/x64/e5400a06c74d41f5b12d430bbaa23d0b/mfxplugin64_hevce_gacc.dll
bd_to_avp/bin/FRIM_x64_version_1.31/x64/e5400a06c74d41f5b12d430bbaa23d0b/plugin.cfg
bd_to_avp/bin/FRIM_x64_version_1.31/x64/libmfxsw64.dll
bd_to_avp/bin/FRIM_x64_version_1.31/x64/mts_frim_dir.bat
bd_to_avp/bin/FRIM_x64_version_1.31/x64/mts_frim_one.bat
bd_to_avp/bin/FRIM_x64_version_1.31/x64/plugins64.reg
bd_to_avp/bin/fx-upscale
bd_to_avp/bin/spatial-media-kit-tool
bd_to_avp/gui/dialog.py
bd_to_avp/gui/main_window.py
bd_to_avp/gui/processing.py
bd_to_avp/gui/util.py
bd_to_avp/gui/widget.py
bd_to_avp/install.py
bd_to_avp/modules/__init__.py
bd_to_avp/modules/audio.py
bd_to_avp/modules/command.py
bd_to_avp/modules/config.py
bd_to_avp/modules/container.py
bd_to_avp/modules/disc.py
bd_to_avp/modules/file.py
bd_to_avp/modules/process.py
bd_to_avp/modules/sub.py
bd_to_avp-0.2.137.dist-info/LICENSE
bd_to_avp-0.2.137.dist-info/METADATA
bd_to_avp-0.2.137.dist-info/WHEEL
bd_to_avp-0.2.137.dist-info/entry_points.txt
bd_to_avp-0.2.137.dist-info/RECORD
