Metadata-Version: 2.1
Name: bd_to_avp
Version: 0.2.137
Summary: Script to convert 3D Blu-ray Discs (and mts) to Apple Vision Pro (MV-HEVC) files
Home-page: https://github.com/cbusillo/BD_to_AVP
Keywords: Blu-ray,3D,Apple Vision Pro,MV-HEVC,Conversion,Vision Pro,BD3D
Author: Chris Busillo
Author-email: info@shinycomputers.com
Requires-Python: >=3.12.4,<3.13
Classifier: Programming Language :: Python :: 3
Requires-Dist: babelfish (>=0.6.1,<0.7.0)
Requires-Dist: ffmpeg-python (>=0.2.0,<0.3.0)
Requires-Dist: humanize (>=4.9.0,<5.0.0)
Requires-Dist: opencv-python (==4.10.0.84)
Requires-Dist: packaging (>=24.1,<25.0)
Requires-Dist: pgsrip (>=0.1.11,<0.2.0)
Requires-Dist: psutil (>=5.9.8,<6.0.0)
Requires-Dist: pygithub (>=2.3.0,<3.0.0)
Requires-Dist: pyside6 (>=6.7.1,<7.0.0)
Requires-Dist: requests (>=2.32.3,<3.0.0)
Requires-Dist: setuptools (>=70.1.1,<71.0.0)
Requires-Dist: tesseract (>=0.1.3,<0.2.0)
Requires-Dist: wakepy (>=0.9.1,<0.10.0)
Project-URL: Documentation, https://github.com/cbusillo/BD_to_AVP
Project-URL: Repository, https://github.com/cbusillo/BD_to_AVP
